_ikc.cpython-39-darwin.so
ikc/__init__.py
ikc-0.4.0.dist-info/licenses/LICENSE
ikc-0.4.0.dist-info/METADATA
ikc-0.4.0.dist-info/WHEEL
ikc-0.4.0.dist-info/top_level.txt
ikc-0.4.0.dist-info/RECORD
