Metadata-Version: 2.4
Name: ikc
Version: 0.4.0
Summary: Fast C++ implementation of Iterative K-Core Clustering with Python bindings
Home-page: https://github.com/vikramr2/ikc
Author: Vikram Ramavarapu
Author-email: vikramr2@illinois.edu
License: MIT
Project-URL: Bug Reports, https://github.com/vikramr2/ikc/issues
Project-URL: Source, https://github.com/vikramr2/ikc
Keywords: graph clustering k-core community-detection network-analysis
Classifier: Development Status :: 4 - Beta
Classifier: Intended Audience :: Science/Research
Classifier: License :: OSI Approved :: MIT License
Classifier: Programming Language :: C++
Classifier: Programming Language :: Python :: 3
Classifier: Programming Language :: Python :: 3.7
Classifier: Programming Language :: Python :: 3.8
Classifier: Programming Language :: Python :: 3.9
Classifier: Programming Language :: Python :: 3.10
Classifier: Programming Language :: Python :: 3.11
Classifier: Programming Language :: Python :: 3.12
Classifier: Topic :: Scientific/Engineering
Requires-Python: >=3.7
License-File: LICENSE
Requires-Dist: pybind11>=2.6.0
Requires-Dist: tqdm>=4.0.0
Dynamic: author
Dynamic: author-email
Dynamic: classifier
Dynamic: description
Dynamic: description-content-type
Dynamic: home-page
Dynamic: keywords
Dynamic: license
Dynamic: license-file
Dynamic: project-url
Dynamic: requires-dist
Dynamic: requires-python
Dynamic: summary
